setup.cfg
setup.py
markup/__init__.py
markup/form.py
markup/markup.py
markup.egg-info/PKG-INFO
markup.egg-info/SOURCES.txt
markup.egg-info/dependency_links.txt
markup.egg-info/entry_points.txt
markup.egg-info/not-zip-safe
markup.egg-info/top_level.txt
