Metadata-Version: 1.0
Name: markup
Version: 0.1
Summary: generate HTML markup programmatically
Home-page: http://www.openplans.org/people/k0s/
Author: Jeff Hammel
Author-email: jhammel@openplans.org
License: GPL
Platform: UNKNOWN
